<annotation>
	<folder>01.musulman</folder>
	<filename>medina_azahara14.jpg</filename>
	<path>D:\Descargas\Dataset\01.musulman\medina_azahara14.jpg</path>
	<source>
		<database>Unknown</database>
	</source>
	<size>
		<width>640</width>
		<height>409</height>
		<depth>3</depth>
	</size>
	<segmented>0</segmented>
	<object>
		<name>arco-herradura</name>
		<pose>Unspecified</pose>
		<truncated>1</truncated>
		<difficult>0</difficult>
		<bndbox>
			<xmin>98</xmin>
			<ymin>262</ymin>
			<xmax>218</xmax>
			<ymax>409</ymax>
		</bndbox>
	</object>
	<object>
		<name>arco-herradura</name>
		<pose>Unspecified</pose>
		<truncated>1</truncated>
		<difficult>0</difficult>
		<bndbox>
			<xmin>212</xmin>
			<ymin>236</ymin>
			<xmax>335</xmax>
			<ymax>409</ymax>
		</bndbox>
	</object>
	<object>
		<name>arco-herradura</name>
		<pose>Unspecified</pose>
		<truncated>0</truncated>
		<difficult>0</difficult>
		<bndbox>
			<xmin>339</xmin>
			<ymin>222</ymin>
			<xmax>499</xmax>
			<ymax>401</ymax>
		</bndbox>
	</object>
</annotation>
