<annotation>
	<folder>Monument</folder>
	<filename>5c878e7d3d3f0.jpg</filename>
	<path>/home/alcasla/Descargas/Monumai-images12.03.20/Monument/5c878e7d3d3f0.jpg</path>
	<source>
		<database>Unknown</database>
	</source>
	<size>
		<width>1024</width>
		<height>1024</height>
		<depth>3</depth>
	</size>
	<segmented>0</segmented>
	<object>
		<name>columna-salomonica</name>
		<pose>Unspecified</pose>
		<truncated>0</truncated>
		<difficult>0</difficult>
		<bndbox>
			<xmin>735</xmin>
			<ymin>467</ymin>
			<xmax>814</xmax>
			<ymax>817</ymax>
		</bndbox>
	</object>
	<object>
		<name>arco-medio-punto</name>
		<pose>Unspecified</pose>
		<truncated>0</truncated>
		<difficult>0</difficult>
		<bndbox>
			<xmin>359</xmin>
			<ymin>429</ymin>
			<xmax>693</xmax>
			<ymax>654</ymax>
		</bndbox>
	</object>
	<object>
		<name>columna-salomonica</name>
		<pose>Unspecified</pose>
		<truncated>0</truncated>
		<difficult>0</difficult>
		<bndbox>
			<xmin>237</xmin>
			<ymin>457</ymin>
			<xmax>320</xmax>
			<ymax>826</ymax>
		</bndbox>
	</object>
	<object>
		<name>fronton-partido</name>
		<pose>Unspecified</pose>
		<truncated>0</truncated>
		<difficult>0</difficult>
		<bndbox>
			<xmin>184</xmin>
			<ymin>203</ymin>
			<xmax>879</xmax>
			<ymax>341</ymax>
		</bndbox>
	</object>
</annotation>
