<annotation><folder>Unknown</folder><filename>5dd7d6e26f601.jpg</filename><path>Unknown</path><source><database>Unknown</database></source><size><width>900</width><height>900</height><depth>3</depth></size><segmented>0</segmented><object><name>arco-medio-punto</name><pose>Unspecified</pose><truncated>0</truncated><difficult>0</difficult><bndbox><xmin>266</xmin><ymin>438</ymin><xmax>710</xmax><ymax>715</ymax></bndbox></object><object><name>fronton-partido</name><pose>Unspecified</pose><truncated>0</truncated><difficult>0</difficult><bndbox><xmin>63</xmin><ymin>104</ymin><xmax>867</xmax><ymax>262</ymax></bndbox></object><object><name>vano-adintelado</name><pose>Unspecified</pose><truncated>0</truncated><difficult>0</difficult><bndbox><xmin>337</xmin><ymin>6</ymin><xmax>612</xmax><ymax>230</ymax></bndbox></object></annotation>