<annotation>
	<folder>04.barroco</folder>
	<filename>catedral_guadix.jpg</filename>
	<path>D:\Descargas\Dataset\04.barroco\catedral_guadix.jpg</path>
	<source>
		<database>Unknown</database>
	</source>
	<size>
		<width>519</width>
		<height>367</height>
		<depth>3</depth>
	</size>
	<segmented>0</segmented>
	<object>
		<name>ojo-de-buey</name>
		<pose>Unspecified</pose>
		<truncated>0</truncated>
		<difficult>0</difficult>
		<bndbox>
			<xmin>251</xmin>
			<ymin>115</ymin>
			<xmax>293</xmax>
			<ymax>154</ymax>
		</bndbox>
	</object>
	<object>
		<name>ojo-de-buey</name>
		<pose>Unspecified</pose>
		<truncated>0</truncated>
		<difficult>0</difficult>
		<bndbox>
			<xmin>57</xmin>
			<ymin>139</ymin>
			<xmax>90</xmax>
			<ymax>174</ymax>
		</bndbox>
	</object>
	<object>
		<name>arco-medio-punto</name>
		<pose>Unspecified</pose>
		<truncated>0</truncated>
		<difficult>0</difficult>
		<bndbox>
			<xmin>127</xmin>
			<ymin>212</ymin>
			<xmax>193</xmax>
			<ymax>255</ymax>
		</bndbox>
	</object>
	<object>
		<name>arco-medio-punto</name>
		<pose>Unspecified</pose>
		<truncated>0</truncated>
		<difficult>0</difficult>
		<bndbox>
			<xmin>442</xmin>
			<ymin>227</ymin>
			<xmax>509</xmax>
			<ymax>265</ymax>
		</bndbox>
	</object>
	<object>
		<name>vano-adintelado</name>
		<pose>Unspecified</pose>
		<truncated>0</truncated>
		<difficult>0</difficult>
		<bndbox>
			<xmin>38</xmin>
			<ymin>258</ymin>
			<xmax>76</xmax>
			<ymax>325</ymax>
		</bndbox>
	</object>
	<object>
		<name>vano-adintelado</name>
		<pose>Unspecified</pose>
		<truncated>0</truncated>
		<difficult>0</difficult>
		<bndbox>
			<xmin>246</xmin>
			<ymin>245</ymin>
			<xmax>297</xmax>
			<ymax>328</ymax>
		</bndbox>
	</object>
</annotation>
