<annotation>
	<folder>06.barroco</folder>
	<filename>iglesia_señora_gracia_estepa2.jpg</filename>
	<path>D:\Descargas\AAampliación2AA\06.barroco\iglesia_señora_gracia_estepa2.jpg</path>
	<source>
		<database>Unknown</database>
	</source>
	<size>
		<width>868</width>
		<height>994</height>
		<depth>3</depth>
	</size>
	<segmented>0</segmented>
	<object>
		<name>fronton-partido</name>
		<pose>Unspecified</pose>
		<truncated>0</truncated>
		<difficult>0</difficult>
		<bndbox>
			<xmin>135</xmin>
			<ymin>552</ymin>
			<xmax>400</xmax>
			<ymax>615</ymax>
		</bndbox>
	</object>
	<object>
		<name>arco-medio-punto</name>
		<pose>Unspecified</pose>
		<truncated>0</truncated>
		<difficult>0</difficult>
		<bndbox>
			<xmin>181</xmin>
			<ymin>666</ymin>
			<xmax>352</xmax>
			<ymax>774</ymax>
		</bndbox>
	</object>
</annotation>
