<annotation>
	<folder>06.barroco</folder>
	<filename>iglesia_salvador_sevilla.jpg</filename>
	<path>D:\Descargas\Dataset\06.barroco\iglesia_salvador_sevilla.jpg</path>
	<source>
		<database>Unknown</database>
	</source>
	<size>
		<width>1200</width>
		<height>803</height>
		<depth>3</depth>
	</size>
	<segmented>0</segmented>
	<object>
		<name>ojo-de-buey</name>
		<pose>Unspecified</pose>
		<truncated>0</truncated>
		<difficult>0</difficult>
		<bndbox>
			<xmin>208</xmin>
			<ymin>379</ymin>
			<xmax>275</xmax>
			<ymax>444</ymax>
		</bndbox>
	</object>
	<object>
		<name>ojo-de-buey</name>
		<pose>Unspecified</pose>
		<truncated>0</truncated>
		<difficult>0</difficult>
		<bndbox>
			<xmin>535</xmin>
			<ymin>122</ymin>
			<xmax>609</xmax>
			<ymax>189</ymax>
		</bndbox>
	</object>
	<object>
		<name>ojo-de-buey</name>
		<pose>Unspecified</pose>
		<truncated>0</truncated>
		<difficult>0</difficult>
		<bndbox>
			<xmin>873</xmin>
			<ymin>364</ymin>
			<xmax>945</xmax>
			<ymax>425</ymax>
		</bndbox>
	</object>
	<object>
		<name>vano-adintelado</name>
		<pose>Unspecified</pose>
		<truncated>0</truncated>
		<difficult>0</difficult>
		<bndbox>
			<xmin>454</xmin>
			<ymin>478</ymin>
			<xmax>686</xmax>
			<ymax>760</ymax>
		</bndbox>
	</object>
	<object>
		<name>vano-adintelado</name>
		<pose>Unspecified</pose>
		<truncated>0</truncated>
		<difficult>0</difficult>
		<bndbox>
			<xmin>119</xmin>
			<ymin>530</ymin>
			<xmax>316</xmax>
			<ymax>750</ymax>
		</bndbox>
	</object>
</annotation>
