<annotation>
	<folder>Monument</folder>
	<filename>5cc07126bd06d.jpg</filename>
	<path>/home/alcasla/Descargas/Monumai-images12.03.20/Monument/5cc07126bd06d.jpg</path>
	<source>
		<database>Unknown</database>
	</source>
	<size>
		<width>1024</width>
		<height>1024</height>
		<depth>3</depth>
	</size>
	<segmented>0</segmented>
	<object>
		<name>arco-apuntado</name>
		<pose>Unspecified</pose>
		<truncated>0</truncated>
		<difficult>0</difficult>
		<bndbox>
			<xmin>297</xmin>
			<ymin>362</ymin>
			<xmax>589</xmax>
			<ymax>555</ymax>
		</bndbox>
	</object>
	<object>
		<name>arco-conopial</name>
		<pose>Unspecified</pose>
		<truncated>0</truncated>
		<difficult>0</difficult>
		<bndbox>
			<xmin>331</xmin>
			<ymin>203</ymin>
			<xmax>568</xmax>
			<ymax>363</ymax>
		</bndbox>
	</object>
</annotation>
