<annotation>
	<folder>03.gotico</folder>
	<filename>iglesia_san_pablo_ubeda9.jpg</filename>
	<path>D:\Descargas\Dataset\03.gotico\iglesia_san_pablo_ubeda9.jpg</path>
	<source>
		<database>Unknown</database>
	</source>
	<size>
		<width>1234</width>
		<height>898</height>
		<depth>3</depth>
	</size>
	<segmented>0</segmented>
	<object>
		<name>arco-trilobulado</name>
		<pose>Unspecified</pose>
		<truncated>0</truncated>
		<difficult>0</difficult>
		<bndbox>
			<xmin>257</xmin>
			<ymin>548</ymin>
			<xmax>365</xmax>
			<ymax>616</ymax>
		</bndbox>
	</object>
	<object>
		<name>arco-trilobulado</name>
		<pose>Unspecified</pose>
		<truncated>0</truncated>
		<difficult>0</difficult>
		<bndbox>
			<xmin>386</xmin>
			<ymin>534</ymin>
			<xmax>513</xmax>
			<ymax>607</ymax>
		</bndbox>
	</object>
	<object>
		<name>arco-apuntado</name>
		<pose>Unspecified</pose>
		<truncated>0</truncated>
		<difficult>0</difficult>
		<bndbox>
			<xmin>183</xmin>
			<ymin>225</ymin>
			<xmax>497</xmax>
			<ymax>507</ymax>
		</bndbox>
	</object>
	<object>
		<name>arco-conopial</name>
		<pose>Unspecified</pose>
		<truncated>0</truncated>
		<difficult>0</difficult>
		<bndbox>
			<xmin>197</xmin>
			<ymin>154</ymin>
			<xmax>424</xmax>
			<ymax>220</ymax>
		</bndbox>
	</object>
	<object>
		<name>arco-conopial</name>
		<pose>Unspecified</pose>
		<truncated>0</truncated>
		<difficult>0</difficult>
		<bndbox>
			<xmin>1018</xmin>
			<ymin>306</ymin>
			<xmax>1197</xmax>
			<ymax>404</ymax>
		</bndbox>
	</object>
</annotation>
